{
  "address": "8acD4ZEnsvqq4iezDrfTBgGGqz1srjQTe816cVjmNnXt",
  "metadata": {
    "name": "escrow_updated",
    "version": "0.1.0",
    "spec": "0.1.0",
    "description": "Created with Anchor"
  },
  "instructions": [
    {
      "name": "create_escrow",
      "docs": [
        "Create escrow - buyer deposits tokens"
      ],
      "discriminator": [
        253,
        215,
        165,
        116,
        36,
        108,
        68,
        80
      ],
      "accounts": [
        {
          "name": "buyer",
          "writable": true,
          "signer": true
        },
        {
          "name": "mintyn_mint"
        },
        {
          "name": "escrow_account",
          "writable": true,
          "pda": {
            "seeds": [
              {
                "kind": "const",
                "value": [
                  101,
                  115,
                  99,
                  114,
                  111,
                  119
                ]
              },
              {
                "kind": "account",
                "path": "buyer"
              },
              {
                "kind": "account",
                "path": "seller"
              },
              {
                "kind": "arg",
                "path": "offer_id"
              }
            ]
          }
        },
        {
          "name": "buyer_token_account",
          "docs": [
            "Buyer's token account (source)"
          ],
          "writable": true
        },
        {
          "name": "escrow_token_account",
          "docs": [
            "Escrow token account (destination) - PDA owned by program"
          ],
          "writable": true,
          "pda": {
            "seeds": [
              {
                "kind": "const",
                "value": [
                  101,
                  115,
                  99,
                  114,
                  111,
                  119
                ]
              },
              {
                "kind": "account",
                "path": "buyer"
              },
              {
                "kind": "account",
                "path": "seller"
              },
              {
                "kind": "arg",
                "path": "offer_id"
              },
              {
                "kind": "const",
                "value": [
                  118,
                  97,
                  117,
                  108,
                  116
                ]
              }
            ]
          }
        },
        {
          "name": "seller"
        },
        {
          "name": "admin"
        },
        {
          "name": "token_program",
          "address": "TokenkegQfeZyiNwAJbNbGKPFXCWuBvf9Ss623VQ5DA"
        },
        {
          "name": "system_program",
          "address": "11111111111111111111111111111111"
        }
      ],
      "args": [
        {
          "name": "amount",
          "type": "u64"
        },
        {
          "name": "offer_id",
          "type": {
            "array": [
              "u8",
              12
            ]
          }
        }
      ]
    },
    {
      "name": "refund_escrow",
      "docs": [
        "Refund escrow - order cancelled (95% buyer, 5% admin)"
      ],
      "discriminator": [
        107,
        186,
        89,
        99,
        26,
        194,
        23,
        204
      ],
      "accounts": [
        {
          "name": "admin",
          "signer": true
        },
        {
          "name": "buyer",
          "writable": true
        },
        {
          "name": "admin_wallet",
          "writable": true
        },
        {
          "name": "mintyn_mint"
        },
        {
          "name": "escrow_account",
          "writable": true,
          "pda": {
            "seeds": [
              {
                "kind": "const",
                "value": [
                  101,
                  115,
                  99,
                  114,
                  111,
                  119
                ]
              },
              {
                "kind": "account",
                "path": "escrow_account.buyer",
                "account": "EscrowAccount"
              },
              {
                "kind": "account",
                "path": "escrow_account.seller",
                "account": "EscrowAccount"
              },
              {
                "kind": "arg",
                "path": "offer_id"
              }
            ]
          }
        },
        {
          "name": "escrow_token_account",
          "docs": [
            "Escrow token account (source)"
          ],
          "writable": true,
          "pda": {
            "seeds": [
              {
                "kind": "const",
                "value": [
                  101,
                  115,
                  99,
                  114,
                  111,
                  119
                ]
              },
              {
                "kind": "account",
                "path": "escrow_account.buyer",
                "account": "EscrowAccount"
              },
              {
                "kind": "account",
                "path": "escrow_account.seller",
                "account": "EscrowAccount"
              },
              {
                "kind": "arg",
                "path": "offer_id"
              },
              {
                "kind": "const",
                "value": [
                  118,
                  97,
                  117,
                  108,
                  116
                ]
              }
            ]
          }
        },
        {
          "name": "buyer_token_account",
          "docs": [
            "Buyer's token account (destination for 95%)"
          ],
          "writable": true
        },
        {
          "name": "admin_token_account",
          "docs": [
            "Admin's token account (destination for 5%)"
          ],
          "writable": true
        },
        {
          "name": "token_program",
          "address": "TokenkegQfeZyiNwAJbNbGKPFXCWuBvf9Ss623VQ5DA"
        }
      ],
      "args": [
        {
          "name": "offer_id",
          "type": {
            "array": [
              "u8",
              12
            ]
          }
        }
      ]
    },
    {
      "name": "release_escrow",
      "docs": [
        "Release escrow - order completed (95% seller, 5% admin)"
      ],
      "discriminator": [
        146,
        253,
        129,
        233,
        20,
        145,
        181,
        206
      ],
      "accounts": [
        {
          "name": "admin",
          "signer": true
        },
        {
          "name": "seller",
          "writable": true
        },
        {
          "name": "admin_wallet",
          "writable": true
        },
        {
          "name": "mintyn_mint"
        },
        {
          "name": "escrow_account",
          "writable": true,
          "pda": {
            "seeds": [
              {
                "kind": "const",
                "value": [
                  101,
                  115,
                  99,
                  114,
                  111,
                  119
                ]
              },
              {
                "kind": "account",
                "path": "escrow_account.buyer",
                "account": "EscrowAccount"
              },
              {
                "kind": "account",
                "path": "escrow_account.seller",
                "account": "EscrowAccount"
              },
              {
                "kind": "arg",
                "path": "offer_id"
              }
            ]
          }
        },
        {
          "name": "escrow_token_account",
          "docs": [
            "Escrow token account (source)"
          ],
          "writable": true,
          "pda": {
            "seeds": [
              {
                "kind": "const",
                "value": [
                  101,
                  115,
                  99,
                  114,
                  111,
                  119
                ]
              },
              {
                "kind": "account",
                "path": "escrow_account.buyer",
                "account": "EscrowAccount"
              },
              {
                "kind": "account",
                "path": "escrow_account.seller",
                "account": "EscrowAccount"
              },
              {
                "kind": "arg",
                "path": "offer_id"
              },
              {
                "kind": "const",
                "value": [
                  118,
                  97,
                  117,
                  108,
                  116
                ]
              }
            ]
          }
        },
        {
          "name": "seller_token_account",
          "docs": [
            "Seller's token account (destination for 95%)"
          ],
          "writable": true
        },
        {
          "name": "admin_token_account",
          "docs": [
            "Admin's token account (destination for 5%)"
          ],
          "writable": true
        },
        {
          "name": "token_program",
          "address": "TokenkegQfeZyiNwAJbNbGKPFXCWuBvf9Ss623VQ5DA"
        }
      ],
      "args": [
        {
          "name": "offer_id",
          "type": {
            "array": [
              "u8",
              12
            ]
          }
        }
      ]
    }
  ],
  "accounts": [
    {
      "name": "EscrowAccount",
      "discriminator": [
        36,
        69,
        48,
        18,
        128,
        225,
        125,
        135
      ]
    }
  ],
  "errors": [
    {
      "code": 6000,
      "name": "EscrowNotFound",
      "msg": "Escrow not found"
    },
    {
      "code": 6001,
      "name": "EscrowAlreadyProcessed",
      "msg": "Escrow already processed"
    },
    {
      "code": 6002,
      "name": "UnauthorizedBuyer",
      "msg": "Unauthorized buyer"
    },
    {
      "code": 6003,
      "name": "UnauthorizedAdmin",
      "msg": "Unauthorized admin"
    },
    {
      "code": 6004,
      "name": "InsufficientBalance",
      "msg": "Insufficient balance"
    },
    {
      "code": 6005,
      "name": "InvalidTokenAccount",
      "msg": "Invalid token account"
    }
  ],
  "types": [
    {
      "name": "EscrowAccount",
      "type": {
        "kind": "struct",
        "fields": [
          {
            "name": "buyer",
            "type": "pubkey"
          },
          {
            "name": "seller",
            "type": "pubkey"
          },
          {
            "name": "admin",
            "type": "pubkey"
          },
          {
            "name": "amount",
            "type": "u64"
          },
          {
            "name": "status",
            "type": "u8"
          },
          {
            "name": "offer_id",
            "type": {
              "array": [
                "u8",
                12
              ]
            }
          },
          {
            "name": "bump",
            "type": "u8"
          }
        ]
      }
    }
  ]
}